tests/djangoproject/__init__.py
tests/djangoproject/celery.py
tests/djangoproject/settings.py
tests/djangoproject/tasks.py
tests/djangoproject/urls.py
websubsub/__init__.py
websubsub/admin.py
websubsub/apps.py
websubsub/models.py
websubsub/views.py
websubsub/management/__init__.py
websubsub/management/commands/__init__.py
websubsub/management/commands/websub_handle_url_changes.py
websubsub/management/commands/websub_purge_all.py
websubsub/management/commands/websub_purge_unresolvable.py
websubsub/management/commands/websub_reset_counters.py
websubsub/management/commands/websub_static_subscribe.py
websubsub/management/commands/websubscribe_static.py
websubsub/migrations/0001_initial.py
websubsub/migrations/0002_auto_20180412_2035.py
websubsub/migrations/0003_subscription_uuid.py
websubsub/migrations/0004_populate_uuid.py
websubsub/migrations/0005_uuid_nonnull.py
websubsub/migrations/0006_auto_20200215_0012.py
websubsub/migrations/0007_auto_20200215_0013.py
websubsub/migrations/0008_subscription_time_created.py
websubsub/migrations/0009_auto_20200215_1654.py
websubsub/migrations/0010_subscription_time_last_event_received.py
websubsub/migrations/0011_subscription_static.py
websubsub/migrations/0012_auto_20200221_1827.py
websubsub/migrations/__init__.py
websubsub/tasks/__init__.py
websubsub/tasks/refresh_subscriptions.py
websubsub/tasks/retry_failed.py
websubsub/tasks/save.py
websubsub/tasks/subscribe.py
websubsub/tasks/unsubscribe.py
websubsub-0.9.3.dist-info/LICENSE
websubsub-0.9.3.dist-info/METADATA
websubsub-0.9.3.dist-info/WHEEL
websubsub-0.9.3.dist-info/top_level.txt
websubsub-0.9.3.dist-info/RECORD
