Metadata-Version: 2.1
Name: websubsub
Version: 0.9.3
Summary: Django websub subscriber
Home-page: https://github.com/Fak3/websubsub
Author: Evstifeev Roman
Author-email: someuniquename@gmail.com
License: MIT
Platform: UNKNOWN
Classifier: Development Status :: 4 - Beta
Classifier: Intended Audience :: Developers
Classifier: License :: OSI Approved :: MIT License
Classifier: Operating System :: Microsoft :: Windows
Classifier: Operating System :: OS Independent
Classifier: Operating System :: POSIX :: Linux
Classifier: Operating System :: MacOS :: MacOS X
Classifier: Operating System :: Android
Classifier: Programming Language :: Python :: 3
Classifier: Topic :: Software Development
Requires-Python: >=3.6
Requires-Dist: celery
Requires-Dist: django
Requires-Dist: django-rest-framework
Requires-Dist: dumblock
Requires-Dist: redis
Requires-Dist: requests
Provides-Extra: develop
Requires-Dist: nose ; extra == 'develop'
Requires-Dist: responses ; extra == 'develop'
